mb/__init__.py
mb/bus.py
mb/commands.py
mb/events.py
mb/exceptions.py
mb/globals.py
mb/injection.py
mb/messages.py
mb/py.typed
mb/contrib/__init__.py
mb/contrib/django/__init__.py
mb/contrib/django/middleware.py
mb/contrib/django/unit_of_work.py
mb/unit_of_work/__init__.py
mb/unit_of_work/uow.py
mb/unit_of_work/utils/__init__.py
mb/unit_of_work/utils/events_collector.py
mb/utils/__init__.py
mb/utils/tracked_handler.py
cqrs_message_bus-0.3b1.dist-info/METADATA
cqrs_message_bus-0.3b1.dist-info/WHEEL
cqrs_message_bus-0.3b1.dist-info/licenses/LICENSE
cqrs_message_bus-0.3b1.dist-info/RECORD
