Metadata-Version: 2.4
Name: cqrs-message-bus
Version: 0.3b1
Summary: Microframework to apply the CQRS pattern over a message bus
Project-URL: Homepage, https://github.com/emarbo/py-cqrs-message-bus
Project-URL: Repository, https://github.com/emarbo/py-cqrs-message-bus
Author-email: Emilio Arenas Bosch <arenas.emilio@gmail.com>
License-Expression: MIT
License-File: LICENSE
Keywords: CQRS,Events,Message bus
Classifier: Development Status :: 4 - Beta
Classifier: Environment :: Web Environment
Classifier: Framework :: Django :: 4
Classifier: Intended Audience :: Developers
Classifier: Operating System :: OS Independent
Classifier: Programming Language :: Python :: 3.10
Classifier: Typing :: Typed
Requires-Python: >=3.10
